Workbook

Sheet 01_Long_Margin
A1: Long Position on Margin: Interactive Model
A3: INPUTS | B3: Value | D3: CALCULATIONS | E3: Value | G3: KEY OUTPUTS | H3: Value
A4: Initial Equity Investment | B4: 10000 | D4: Total Stock Purchased | E4: =B4+B5 -> 20000 | G4: ROI | H4: =E11 -> -0.456
A5: Amount Borrowed | B5: 10000 | D5: Shares Purchased | E5: =E4/B6 -> 400 | G5: Current Margin Ratio | H5: =E12 -> 0.375
A6: Initial Stock Price | B6: 50 | D6: Capital Gain on Stock | E6: =E5*(B7-B6) -> -4000 | G6: Margin Call Price | H6: =E13 -> 35.714286
A7: Ending Stock Price | B7: 40 | D7: Dividends Received | E7: =E5*B8 -> 240 | G7: Leverage Multiple | H7: =E4/B4 -> 2
A8: Cash Dividends During Hold Period | B8: 0.6 | D8: Interest on Margin Loan | E8: =B5*B9*(B10/12) -> 800 | G8: Margin Call Status | H8: =IF(B7<=E13,"MARGIN CALL / Below Threshold","Safe") -> Safe
A9: Interest Rate on Margin Loan | B9: 0.08 | D9: Net Income | E9: =E6+E7-E8 -> -4560
A10: Holding Period in Months | B10: 12 | D10: Initial Investment | E10: =B4 -> 10000
A11: Maintenance Margin Percentage | B11: 0.3 | D11: Return on Investment | E11: =E9/E10 -> -0.456
D12: Margin Based on Ending Price | E12: =((E5*B7)-B5)/(E5*B7) -> 0.375
D13: Price for Margin Call | E13: =B5/(E5*(1-B11)) -> 35.714286
A15: Ending Stock Price | B15: ROI with Margin | C15: ROI with No Margin | D15: Margin Ratio
A16: 20 | B16: =((($E$5*A16)-$E$4)+($E$5*$B$8)-$E$8)/$B$4 -> -1.256 | C16: =((($B$4/$B$6)*A16)-$B$4+(($B$4/$B$6)*$B$8))/$B$4 -> -0.588 | D16: =((($E$5*A16)-$B$5)/($E$5*A16)) -> -0.25
A17: 25 | B17: =((($E$5*A17)-$E$4)+($E$5*$B$8)-$E$8)/$B$4 -> -1.056 | C17: =((($B$4/$B$6)*A17)-$B$4+(($B$4/$B$6)*$B$8))/$B$4 -> -0.488 | D17: =((($E$5*A17)-$B$5)/($E$5*A17)) -> 0
A18: 30 | B18: =((($E$5*A18)-$E$4)+($E$5*$B$8)-$E$8)/$B$4 -> -0.856 | C18: =((($B$4/$B$6)*A18)-$B$4+(($B$4/$B$6)*$B$8))/$B$4 -> -0.388 | D18: =((($E$5*A18)-$B$5)/($E$5*A18)) -> 0.16666667
A19: 35 | B19: =((($E$5*A19)-$E$4)+($E$5*$B$8)-$E$8)/$B$4 -> -0.656 | C19: =((($B$4/$B$6)*A19)-$B$4+(($B$4/$B$6)*$B$8))/$B$4 -> -0.288 | D19: =((($E$5*A19)-$B$5)/($E$5*A19)) -> 0.28571429
A20: 40 | B20: =((($E$5*A20)-$E$4)+($E$5*$B$8)-$E$8)/$B$4 -> -0.456 | C20: =((($B$4/$B$6)*A20)-$B$4+(($B$4/$B$6)*$B$8))/$B$4 -> -0.188 | D20: =((($E$5*A20)-$B$5)/($E$5*A20)) -> 0.375
A21: 45 | B21: =((($E$5*A21)-$E$4)+($E$5*$B$8)-$E$8)/$B$4 -> -0.256 | C21: =((($B$4/$B$6)*A21)-$B$4+(($B$4/$B$6)*$B$8))/$B$4 -> -0.088 | D21: =((($E$5*A21)-$B$5)/($E$5*A21)) -> 0.44444444
A22: 50 | B22: =((($E$5*A22)-$E$4)+($E$5*$B$8)-$E$8)/$B$4 -> -0.056 | C22: =((($B$4/$B$6)*A22)-$B$4+(($B$4/$B$6)*$B$8))/$B$4 -> 0.012 | D22: =((($E$5*A22)-$B$5)/($E$5*A22)) -> 0.5
A23: 55 | B23: =((($E$5*A23)-$E$4)+($E$5*$B$8)-$E$8)/$B$4 -> 0.144 | C23: =((($B$4/$B$6)*A23)-$B$4+(($B$4/$B$6)*$B$8))/$B$4 -> 0.112 | D23: =((($E$5*A23)-$B$5)/($E$5*A23)) -> 0.54545455
A24: 60 | B24: =((($E$5*A24)-$E$4)+($E$5*$B$8)-$E$8)/$B$4 -> 0.344 | C24: =((($B$4/$B$6)*A24)-$B$4+(($B$4/$B$6)*$B$8))/$B$4 -> 0.212 | D24: =((($E$5*A24)-$B$5)/($E$5*A24)) -> 0.58333333
A25: 65 | B25: =((($E$5*A25)-$E$4)+($E$5*$B$8)-$E$8)/$B$4 -> 0.544 | C25: =((($B$4/$B$6)*A25)-$B$4+(($B$4/$B$6)*$B$8))/$B$4 -> 0.312 | D25: =((($E$5*A25)-$B$5)/($E$5*A25)) -> 0.61538462
A26: 70 | B26: =((($E$5*A26)-$E$4)+($E$5*$B$8)-$E$8)/$B$4 -> 0.744 | C26: =((($B$4/$B$6)*A26)-$B$4+(($B$4/$B$6)*$B$8))/$B$4 -> 0.412 | D26: =((($E$5*A26)-$B$5)/($E$5*A26)) -> 0.64285714
A27: 75 | B27: =((($E$5*A27)-$E$4)+($E$5*$B$8)-$E$8)/$B$4 -> 0.944 | C27: =((($B$4/$B$6)*A27)-$B$4+(($B$4/$B$6)*$B$8))/$B$4 -> 0.512 | D27: =((($E$5*A27)-$B$5)/($E$5*A27)) -> 0.66666667
A28: 80 | B28: =((($E$5*A28)-$E$4)+($E$5*$B$8)-$E$8)/$B$4 -> 1.144 | C28: =((($B$4/$B$6)*A28)-$B$4+(($B$4/$B$6)*$B$8))/$B$4 -> 0.612 | D28: =((($E$5*A28)-$B$5)/($E$5*A28)) -> 0.6875

Sheet 02_Short_Sale
A1: Short Sale and Margin Call Model
A3: INPUTS | B3: Value | D3: RETURN ON SHORT SALE | E3: Value
A4: Initial Investment / Margin Deposit | B4: 50000 | D4: Short Sale Proceeds | E4: =B5*B6 -> 100000
A5: Initial Stock Price | B5: 100 | D5: Capital Gain on Stock | E5: =B6*(B5-B7) -> 30000
A6: Number of Shares Sold Short | B6: 1000 | D6: Dividends Paid | E6: =B6*B8 -> 0
A7: Ending Stock Price | B7: 70 | D7: Net Income | E7: =E5-E6 -> 30000
A8: Cash Dividends Per Share | B8: 0 | D8: Initial Investment | E8: =B4 -> 50000
A9: Initial Margin Percentage | B9: 0.5 | D9: Return on Investment | E9: =E7/E8 -> 0.6
A10: Maintenance Margin Percentage | B10: 0.3
D12: MARGIN POSITIONS | E12: Value
D13: Margin Based on Ending Price | E13: =(B4+(B5*B6)-E6-(B6*B7))/(B6*B7) -> 1.1428571
D14: Price for Margin Call | E14: =(B4+(B5*B6)-E6)/(B6*(1+B10)) -> 115.38462
D15: Margin Call Status | E15: =IF(B7>=E14,"MARGIN CALL / Above Threshold","Safe") -> Safe
A18: Ending Stock Price | B18: Return on Investment | C18: Margin Ratio
A19: 10 | B19: =($B$6*($B$5-A19)-($B$6*$B$8))/$B$4 -> 1.8 | C19: =($B$4+($B$5*$B$6)-($B$6*$B$8)-($B$6*A19))/($B$6*A19) -> 14
A20: 20 | B20: =($B$6*($B$5-A20)-($B$6*$B$8))/$B$4 -> 1.6 | C20: =($B$4+($B$5*$B$6)-($B$6*$B$8)-($B$6*A20))/($B$6*A20) -> 6.5 | E20: =80/70 -> 1.1428571
A21: 30 | B21: =($B$6*($B$5-A21)-($B$6*$B$8))/$B$4 -> 1.4 | C21: =($B$4+($B$5*$B$6)-($B$6*$B$8)-($B$6*A21))/($B$6*A21) -> 4
A22: 40 | B22: =($B$6*($B$5-A22)-($B$6*$B$8))/$B$4 -> 1.2 | C22: =($B$4+($B$5*$B$6)-($B$6*$B$8)-($B$6*A22))/($B$6*A22) -> 2.75
A23: 50 | B23: =($B$6*($B$5-A23)-($B$6*$B$8))/$B$4 -> 1 | C23: =($B$4+($B$5*$B$6)-($B$6*$B$8)-($B$6*A23))/($B$6*A23) -> 2
A24: 60 | B24: =($B$6*($B$5-A24)-($B$6*$B$8))/$B$4 -> 0.8 | C24: =($B$4+($B$5*$B$6)-($B$6*$B$8)-($B$6*A24))/($B$6*A24) -> 1.5
A25: 70 | B25: =($B$6*($B$5-A25)-($B$6*$B$8))/$B$4 -> 0.6 | C25: =($B$4+($B$5*$B$6)-($B$6*$B$8)-($B$6*A25))/($B$6*A25) -> 1.1428571
A26: 80 | B26: =($B$6*($B$5-A26)-($B$6*$B$8))/$B$4 -> 0.4 | C26: =($B$4+($B$5*$B$6)-($B$6*$B$8)-($B$6*A26))/($B$6*A26) -> 0.875
A27: 90 | B27: =($B$6*($B$5-A27)-($B$6*$B$8))/$B$4 -> 0.2 | C27: =($B$4+($B$5*$B$6)-($B$6*$B$8)-($B$6*A27))/($B$6*A27) -> 0.66666667
A28: 100 | B28: =($B$6*($B$5-A28)-($B$6*$B$8))/$B$4 -> 0 | C28: =($B$4+($B$5*$B$6)-($B$6*$B$8)-($B$6*A28))/($B$6*A28) -> 0.5
A29: 110 | B29: =($B$6*($B$5-A29)-($B$6*$B$8))/$B$4 -> -0.2 | C29: =($B$4+($B$5*$B$6)-($B$6*$B$8)-($B$6*A29))/($B$6*A29) -> 0.36363636
A30: 120 | B30: =($B$6*($B$5-A30)-($B$6*$B$8))/$B$4 -> -0.4 | C30: =($B$4+($B$5*$B$6)-($B$6*$B$8)-($B$6*A30))/($B$6*A30) -> 0.25
A31: 130 | B31: =($B$6*($B$5-A31)-($B$6*$B$8))/$B$4 -> -0.6 | C31: =($B$4+($B$5*$B$6)-($B$6*$B$8)-($B$6*A31))/($B$6*A31) -> 0.15384615
A32: 140 | B32: =($B$6*($B$5-A32)-($B$6*$B$8))/$B$4 -> -0.8 | C32: =($B$4+($B$5*$B$6)-($B$6*$B$8)-($B$6*A32))/($B$6*A32) -> 0.071428571
... A35: 170 | B35: =($B$6*($B$5-A35)-($B$6*$B$8))/$B$4 -> -1.4 | C35: =($B$4+($B$5*$B$6)-($B$6*$B$8)-($B$6*A35))/($B$6*A35) -> -0.11764706

Sheet 03_Sensitivity
A1: Combined Sensitivity: Margin Curves and Leverage Effects
A3: Stock Price | B3: Long ROI | C3: Long Margin Ratio | D3: Short ROI | E3: Short Margin Ratio
A4: 10 | B4: =((('01_Long_Margin'!$E$5*A4)-'01_Long_Margin'!$E$4)+('01_Long_Margin'!$E$5*'01_Long_Margin'!$B$8)-'01_Long_Margin'!$E$8)/'01_Long_Margin'!$B$4 -> -1.656 | C4: =((('01_Long_Margin'!$E$5*A4)-'01_Long_Margin'!$B$5)/('01_Long_Margin'!$E$5*A4)) -> -1.5 | D4: =('02_Short_Sale'!$B$6*('02_Short_Sale'!$B$5-A4)-('02_Short_Sale'!$B$6*'02_Short_Sale'!$B$8))/'02_Short_Sale'!$B$4 -> 1.8 | E4: =('02_Short_Sale'!$B$4+('02_Short_Sale'!$B$5*'02_Short_Sale'!$B$6)-('02_Short_Sale'!$B$6*'02_Short_Sale'!$B$8)-('02_Short_Sale'!$B$6*A4))/('02_Short_Sale'!$B$6*A4) -> 14
A5: 15 | B5: =((('01_Long_Margin'!$E$5*A5)-'01_Long_Margin'!$E$4)+('01_Long_Margin'!$E$5*'01_Long_Margin'!$B$8)-'01_Long_Margin'!$E$8)/'01_Long_Margin'!$B$4 -> -1.456 | C5: =((('01_Long_Margin'!$E$5*A5)-'01_Long_Margin'!$B$5)/('01_Long_Margin'!$E$5*A5)) -> -0.66666667 | D5: =('02_Short_Sale'!$B$6*('02_Short_Sale'!$B$5-A5)-('02_Short_Sale'!$B$6*'02_Short_Sale'!$B$8))/'02_Short_Sale'!$B$4 -> 1.7 | E5: =('02_Short_Sale'!$B$4+('02_Short_Sale'!$B$5*'02_Short_Sale'!$B$6)-('02_Short_Sale'!$B$6*'02_Short_Sale'!$B$8)-('02_Short_Sale'!$B$6*A5))/('02_Short_Sale'!$B$6*A5) -> 9
A6: 20 | B6: =((('01_Long_Margin'!$E$5*A6)-'01_Long_Margin'!$E$4)+('01_Long_Margin'!$E$5*'01_Long_Margin'!$B$8)-'01_Long_Margin'!$E$8)/'01_Long_Margin'!$B$4 -> -1.256 | C6: =((('01_Long_Margin'!$E$5*A6)-'01_Long_Margin'!$B$5)/('01_Long_Margin'!$E$5*A6)) -> -0.25 | D6: =('02_Short_Sale'!$B$6*('02_Short_Sale'!$B$5-A6)-('02_Short_Sale'!$B$6*'02_Short_Sale'!$B$8))/'02_Short_Sale'!$B$4 -> 1.6 | E6: =('02_Short_Sale'!$B$4+('02_Short_Sale'!$B$5*'02_Short_Sale'!$B$6)-('02_Short_Sale'!$B$6*'02_Short_Sale'!$B$8)-('02_Short_Sale'!$B$6*A6))/('02_Short_Sale'!$B$6*A6) -> 6.5
A7: 25 | B7: =((('01_Long_Margin'!$E$5*A7)-'01_Long_Margin'!$E$4)+('01_Long_Margin'!$E$5*'01_Long_Margin'!$B$8)-'01_Long_Margin'!$E$8)/'01_Long_Margin'!$B$4 -> -1.056 | C7: =((('01_Long_Margin'!$E$5*A7)-'01_Long_Margin'!$B$5)/('01_Long_Margin'!$E$5*A7)) -> 0 | D7: =('02_Short_Sale'!$B$6*('02_Short_Sale'!$B$5-A7)-('02_Short_Sale'!$B$6*'02_Short_Sale'!$B$8))/'02_Short_Sale'!$B$4 -> 1.5 | E7: =('02_Short_Sale'!$B$4+('02_Short_Sale'!$B$5*'02_Short_Sale'!$B$6)-('02_Short_Sale'!$B$6*'02_Short_Sale'!$B$8)-('02_Short_Sale'!$B$6*A7))/('02_Short_Sale'!$B$6*A7) -> 5
A8: 30 | B8: =((('01_Long_Margin'!$E$5*A8)-'01_Long_Margin'!$E$4)+('01_Long_Margin'!$E$5*'01_Long_Margin'!$B$8)-'01_Long_Margin'!$E$8)/'01_Long_Margin'!$B$4 -> -0.856 | C8: =((('01_Long_Margin'!$E$5*A8)-'01_Long_Margin'!$B$5)/('01_Long_Margin'!$E$5*A8)) -> 0.16666667 | D8: =('02_Short_Sale'!$B$6*('02_Short_Sale'!$B$5-A8)-('02_Short_Sale'!$B$6*'02_Short_Sale'!$B$8))/'02_Short_Sale'!$B$4 -> 1.4 | E8: =('02_Short_Sale'!$B$4+('02_Short_Sale'!$B$5*'02_Short_Sale'!$B$6)-('02_Short_Sale'!$B$6*'02_Short_Sale'!$B$8)-('02_Short_Sale'!$B$6*A8))/('02_Short_Sale'!$B$6*A8) -> 4
A9: 35 | B9: =((('01_Long_Margin'!$E$5*A9)-'01_Long_Margin'!$E$4)+('01_Long_Margin'!$E$5*'01_Long_Margin'!$B$8)-'01_Long_Margin'!$E$8)/'01_Long_Margin'!$B$4 -> -0.656 | C9: =((('01_Long_Margin'!$E$5*A9)-'01_Long_Margin'!$B$5)/('01_Long_Margin'!$E$5*A9)) -> 0.28571429 | D9: =('02_Short_Sale'!$B$6*('02_Short_Sale'!$B$5-A9)-('02_Short_Sale'!$B$6*'02_Short_Sale'!$B$8))/'02_Short_Sale'!$B$4 -> 1.3 | E9: =('02_Short_Sale'!$B$4+('02_Short_Sale'!$B$5*'02_Short_Sale'!$B$6)-('02_Short_Sale'!$B$6*'02_Short_Sale'!$B$8)-('02_Short_Sale'!$B$6*A9))/('02_Short_Sale'!$B$6*A9) -> 3.2857143
A10: 40 | B10: =((('01_Long_Margin'!$E$5*A10)-'01_Long_Margin'!$E$4)+('01_Long_Margin'!$E$5*'01_Long_Margin'!$B$8)-'01_Long_Margin'!$E$8)/'01_Long_Margin'!$B$4 -> -0.456 | C10: =((('01_Long_Margin'!$E$5*A10)-'01_Long_Margin'!$B$5)/('01_Long_Margin'!$E$5*A10)) -> 0.375 | D10: =('02_Short_Sale'!$B$6*('02_Short_Sale'!$B$5-A10)-('02_Short_Sale'!$B$6*'02_Short_Sale'!$B$8))/'02_Short_Sale'!$B$4 -> 1.2 | E10: =('02_Short_Sale'!$B$4+('02_Short_Sale'!$B$5*'02_Short_Sale'!$B$6)-('02_Short_Sale'!$B$6*'02_Short_Sale'!$B$8)-('02_Short_Sale'!$B$6*A10))/('02_Short_Sale'!$B$6*A10) -> 2.75
A11: 45 | B11: =((('01_Long_Margin'!$E$5*A11)-'01_Long_Margin'!$E$4)+('01_Long_Margin'!$E$5*'01_Long_Margin'!$B$8)-'01_Long_Margin'!$E$8)/'01_Long_Margin'!$B$4 -> -0.256 | C11: =((('01_Long_Margin'!$E$5*A11)-'01_Long_Margin'!$B$5)/('01_Long_Margin'!$E$5*A11)) -> 0.44444444 | D11: =('02_Short_Sale'!$B$6*('02_Short_Sale'!$B$5-A11)-('02_Short_Sale'!$B$6*'02_Short_Sale'!$B$8))/'02_Short_Sale'!$B$4 -> 1.1 | E11: =('02_Short_Sale'!$B$4+('02_Short_Sale'!$B$5*'02_Short_Sale'!$B$6)-('02_Short_Sale'!$B$6*'02_Short_Sale'!$B$8)-('02_Short_Sale'!$B$6*A11))/('02_Short_Sale'!$B$6*A11) -> 2.3333333
A12: 50 | B12: =((('01_Long_Margin'!$E$5*A12)-'01_Long_Margin'!$E$4)+('01_Long_Margin'!$E$5*'01_Long_Margin'!$B$8)-'01_Long_Margin'!$E$8)/'01_Long_Margin'!$B$4 -> -0.056 | C12: =((('01_Long_Margin'!$E$5*A12)-'01_Long_Margin'!$B$5)/('01_Long_Margin'!$E$5*A12)) -> 0.5 | D12: =('02_Short_Sale'!$B$6*('02_Short_Sale'!$B$5-A12)-('02_Short_Sale'!$B$6*'02_Short_Sale'!$B$8))/'02_Short_Sale'!$B$4 -> 1 | E12: =('02_Short_Sale'!$B$4+('02_Short_Sale'!$B$5*'02_Short_Sale'!$B$6)-('02_Short_Sale'!$B$6*'02_Short_Sale'!$B$8)-('02_Short_Sale'!$B$6*A12))/('02_Short_Sale'!$B$6*A12) -> 2
A13: 55 | B13: =((('01_Long_Margin'!$E$5*A13)-'01_Long_Margin'!$E$4)+('01_Long_Margin'!$E$5*'01_Long_Margin'!$B$8)-'01_Long_Margin'!$E$8)/'01_Long_Margin'!$B$4 -> 0.144 | C13: =((('01_Long_Margin'!$E$5*A13)-'01_Long_Margin'!$B$5)/('01_Long_Margin'!$E$5*A13)) -> 0.54545455 | D13: =('02_Short_Sale'!$B$6*('02_Short_Sale'!$B$5-A13)-('02_Short_Sale'!$B$6*'02_Short_Sale'!$B$8))/'02_Short_Sale'!$B$4 -> 0.9 | E13: =('02_Short_Sale'!$B$4+('02_Short_Sale'!$B$5*'02_Short_Sale'!$B$6)-('02_Short_Sale'!$B$6*'02_Short_Sale'!$B$8)-('02_Short_Sale'!$B$6*A13))/('02_Short_Sale'!$B$6*A13) -> 1.7272727
A14: 60 | B14: =((('01_Long_Margin'!$E$5*A14)-'01_Long_Margin'!$E$4)+('01_Long_Margin'!$E$5*'01_Long_Margin'!$B$8)-'01_Long_Margin'!$E$8)/'01_Long_Margin'!$B$4 -> 0.344 | C14: =((('01_Long_Margin'!$E$5*A14)-'01_Long_Margin'!$B$5)/('01_Long_Margin'!$E$5*A14)) -> 0.58333333 | D14: =('02_Short_Sale'!$B$6*('02_Short_Sale'!$B$5-A14)-('02_Short_Sale'!$B$6*'02_Short_Sale'!$B$8))/'02_Short_Sale'!$B$4 -> 0.8 | E14: =('02_Short_Sale'!$B$4+('02_Short_Sale'!$B$5*'02_Short_Sale'!$B$6)-('02_Short_Sale'!$B$6*'02_Short_Sale'!$B$8)-('02_Short_Sale'!$B$6*A14))/('02_Short_Sale'!$B$6*A14) -> 1.5
A15: 65 | B15: =((('01_Long_Margin'!$E$5*A15)-'01_Long_Margin'!$E$4)+('01_Long_Margin'!$E$5*'01_Long_Margin'!$B$8)-'01_Long_Margin'!$E$8)/'01_Long_Margin'!$B$4 -> 0.544 | C15: =((('01_Long_Margin'!$E$5*A15)-'01_Long_Margin'!$B$5)/('01_Long_Margin'!$E$5*A15)) -> 0.61538462 | D15: =('02_Short_Sale'!$B$6*('02_Short_Sale'!$B$5-A15)-('02_Short_Sale'!$B$6*'02_Short_Sale'!$B$8))/'02_Short_Sale'!$B$4 -> 0.7 | E15: =('02_Short_Sale'!$B$4+('02_Short_Sale'!$B$5*'02_Short_Sale'!$B$6)-('02_Short_Sale'!$B$6*'02_Short_Sale'!$B$8)-('02_Short_Sale'!$B$6*A15))/('02_Short_Sale'!$B$6*A15) -> 1.3076923
... A38: 180 | B38: =((('01_Long_Margin'!$E$5*A38)-'01_Long_Margin'!$E$4)+('01_Long_Margin'!$E$5*'01_Long_Margin'!$B$8)-'01_Long_Margin'!$E$8)/'01_Long_Margin'!$B$4 -> 5.144 | C38: =((('01_Long_Margin'!$E$5*A38)-'01_Long_Margin'!$B$5)/('01_Long_Margin'!$E$5*A38)) -> 0.86111111 | D38: =('02_Short_Sale'!$B$6*('02_Short_Sale'!$B$5-A38)-('02_Short_Sale'!$B$6*'02_Short_Sale'!$B$8))/'02_Short_Sale'!$B$4 -> -1.6 | E38: =('02_Short_Sale'!$B$4+('02_Short_Sale'!$B$5*'02_Short_Sale'!$B$6)-('02_Short_Sale'!$B$6*'02_Short_Sale'!$B$8)-('02_Short_Sale'!$B$6*A38))/('02_Short_Sale'!$B$6*A38) -> -0.16666667

Sheet 04_Dashboard
A1: Securities Analysis Teaching Dashboard: Margin and Short Sales
A3: Long Position KPIs | B3: Value | D3: Short Sale KPIs | E3: Value | G3: Instructions
A4: ROI | B4: ='01_Long_Margin'!H4 -> -0.456 | D4: ROI | E4: ='02_Short_Sale'!E9 -> 0.6 | G4: 1. Change the yellow input cells in sheets 01 and 02.
A5: Margin Ratio | B5: ='01_Long_Margin'!H5 -> 0.375 | D5: Margin Ratio | E5: ='02_Short_Sale'!E13 -> 1.1428571 | G5: 2. Observe how leverage magnifies returns and losses.
A6: Margin Call Price | B6: ='01_Long_Margin'!H6 -> 35.714286 | D6: Margin Call Price | E6: ='02_Short_Sale'!E14 -> 115.38462 | G6: 3. Compare long margin call price with short sale margin call price.
A7: Leverage Multiple | B7: ='01_Long_Margin'!H7 -> 2 | D7: Net Income | E7: ='02_Short_Sale'!E7 -> 30000 | G7: 4. Use curves in Sensitivity sheet for class discussion.
A8: Status | B8: ='01_Long_Margin'!H8 -> Safe | D8: Status | E8: ='02_Short_Sale'!E15 -> Safe | G8: 5. Input cells contain comments explaining their meaning.

Sheet Notes
A1: Model Notes and Classroom Use
A3: Section | B3: Note
A4: Purpose | B4: Interactive teaching model for buying on margin and short selling using the textbook numerical illustrations.
A5: Inputs | B5: Yellow cells are hardcoded assumptions and can be changed for scenario analysis.
A6: Outputs | B6: Green cells summarize key outputs: ROI, margin ratio, margin call price, leverage, and status.
A7: Long Margin Equation | B7: Margin ratio = (Market value of stock - broker loan) / market value of stock. Margin call price = Loan / [Shares × (1 - maintenance margin)].
A8: Short Sale Equation | B8: Margin ratio = (Margin deposit + short sale proceeds - value of shares owed - dividends paid) / value of shares owed. Margin call price = (Deposit + proceeds - dividends paid) / [Shares × (1 + maintenance margin)].
A9: Classroom Application | B9: Ask students to change maintenance margin, ending price, dividend, and borrowed amount to observe changes in ROI and margin call status.
