Workbook

Sheet Read Me
B1: EFFICIENT FRONTIER & PORTFOLIO THEORY — MBA FINANCE TEACHING WORKBOOK | I1: Srikanth Potharla is an accounting and finance educator with over fifteen years of teaching and industry-oriented experience. Currently serving as Assistant Professor at ICFAI Business School, Hyderabad, he specializes in financial modeling using Excel, valuation, and data analytics. His work bridges theory and practice through structured models, real-world applications, and hands-on learning resources designed for MBA, professional, and global learners.
B3: WORKBOOK OBJECTIVE
B4: Builds the Two-Asset Efficient Frontier step by step and connects it to the Capital Market Line (CML), CAPM, and Security Market Line (SML). All 11 sheets are formula-driven and update live when Inputs change. Designed for MBA Finance classroom demonstration by Dr. Srikanth Potharla, ICFAI Business School, Hyderabad.
B6: LEARNING OUTCOMES
B7: 1. Calculate two-asset portfolio return: E(Rp) = wA × E(RA) + wB × E(RB)
B8: 2. Calculate portfolio variance and standard deviation using the covariance formula
B9: 3. Understand how changing weights moves a portfolio along the opportunity set
B10: 4. See how correlation (ρ) shapes the degree of diversification benefit
B11: 5. Identify the Minimum Variance Portfolio (MVP) analytically and numerically
B12: 6. Distinguish efficient portfolios (upper frontier) from dominated portfolios (lower)
B13: 7. Understand how the Capital Market Line (CML) emerges by introducing a risk-free asset
B14: 8. Apply CAPM: Required Return = Rf + β × (E(Rm) – Rf) for any beta
B15: 9. Use SML alpha to make buy, hold, or sell investment decisions
... B31: • Input values use BLUE text on YELLOW background. Formula cells use BLACK text (formula-driven).

Sheet Inputs
B1: INPUTS PANEL — Edit ONLY the YELLOW Cells Below
C3: Parameter | D3: Input Value | E3: Notes / Interpretation
B4: ASSET A (Equity / Higher Return / Aggressive)
C5: Asset A – Name | D5: Equity (Aggressive) | E5: Text label used in chart legends
C6: Asset A – Expected Annual Return E(RA) | D6: 0.15 | E6: Enter as decimal: 0.15 = 15%
C7: Asset A – Annual Standard Deviation σA | D7: 0.25 | E7: Enter as decimal: 0.25 = 25%
B9: ASSET B (Bond / Lower Return / Defensive)
C10: Asset B – Name | D10: Bond (Defensive) | E10: Text label used in chart legends
C11: Asset B – Expected Annual Return E(RB) | D11: 0.08 | E11: Enter as decimal: 0.08 = 8%
C12: Asset B – Annual Standard Deviation σB | D12: 0.12 | E12: Enter as decimal: 0.12 = 12%
B14: CORRELATION
C15: Correlation Coefficient ρAB | D15: 0.3 | E15: DATA VALIDATED: Must be between –1.00 and +1.00
D17: ρ = +1.00 → No diversification benefit — frontier becomes a straight line
D18: ρ = 0.00 → Strong diversification benefit — frontier curves noticeably left
D19: ρ = –1.00 → Perfect hedge — risk can theoretically be reduced to zero
B21: MARKET PARAMETERS (for CML, CAPM & SML)
C22: Risk-Free Rate Rf | D22: 0.05 | E22: T-bill / G-Sec rate. Enter decimal: 0.05 = 5%
C23: Expected Market Return E(Rm) | D23: 0.12 | E23: Nifty 500 expected return. Enter decimal.
C24: Market Standard Deviation σm | D24: 0.18 | E24: Market portfolio std dev. Enter decimal.
C26: Market Risk Premium (auto-calculated) | D26: =Inputs!$D$23-Inputs!$D$22 -> 0.07 | E26: Calc: E(Rm) – Rf | Links to Inputs above

Sheet Two-Asset Frontier Calculations
A1: TWO-ASSET FRONTIER CALCULATIONS — 101 Portfolios (wA from 0% to 100%)
A2: # | B2: wA (Asset A) | C2: wB (Asset B) | D2: E(Rp) Return | E2: Wtd Avg Risk | F2: Variance σp² | G2: Std Dev σp | H2: Divers. Benefit | I2: Sharpe Ratio | J2: Eff Frontier X (σp or NA) | K2: Eff Frontier Y (E(Rp) or NA) | L2: Opp Set X (σp) | M2: Opp Set Y (E(Rp)) | N2: MVP Flag
A3: 1 | B3: =(ROW()-3)*0.01 -> 0 | C3: =1-B3 -> 1 | D3: =B3*Inputs!$D$6+C3*Inputs!$D$11 -> 0.08 | E3: =B3*Inputs!$D$7+C3*Inputs!$D$12 -> 0.12 | F3: =B3^2*Inputs!$D$7^2+C3^2*Inputs!$D$12^2+2*B3*C3*Inputs!$D$7*Inputs!$D$12*Inputs!$D$15 -> 0.0144 | G3: =SQRT(F3) -> 0.12 | H3: =E3-G3 -> 0 | I3: =IFERROR((D3-Inputs!$D$22)/G3,"") -> 0.25 | J3: =IF(D3>=INDEX($D$3:$D$103,MATCH(MIN($G$3:$G$103),$G$3:$G$103,0)),G3,NA()) -> #N/A | K3: =IF(D3>=INDEX($D$3:$D$103,MATCH(MIN($G$3:$G$103),$G$3:$G$103,0)),D3,NA()) -> #N/A | L3: =G3 -> 0.12 | M3: =D3 -> 0.08 | N3: =IF(ABS(G3-MIN($G$3:$G$103))<0.00001,"★ MVP","")
A4: 2 | B4: =(ROW()-3)*0.01 -> 0.01 | C4: =1-B4 -> 0.99 | D4: =B4*Inputs!$D$6+C4*Inputs!$D$11 -> 0.0807 | E4: =B4*Inputs!$D$7+C4*Inputs!$D$12 -> 0.1213 | F4: =B4^2*Inputs!$D$7^2+C4^2*Inputs!$D$12^2+2*B4*C4*Inputs!$D$7*Inputs!$D$12*Inputs!$D$15 -> 0.01429789 | G4: =SQRT(F4) -> 0.11957378 | H4: =E4-G4 -> 0.0017262152 | I4: =IFERROR((D4-Inputs!$D$22)/G4,"") -> 0.25674524 | J4: =IF(D4>=INDEX($D$3:$D$103,MATCH(MIN($G$3:$G$103),$G$3:$G$103,0)),G4,NA()) -> #N/A | K4: =IF(D4>=INDEX($D$3:$D$103,MATCH(MIN($G$3:$G$103),$G$3:$G$103,0)),D4,NA()) -> #N/A | L4: =G4 -> 0.11957378 | M4: =D4 -> 0.0807 | N4: =IF(ABS(G4-MIN($G$3:$G$103))<0.00001,"★ MVP","")
A5: 3 | B5: =(ROW()-3)*0.01 -> 0.02 | C5: =1-B5 -> 0.98 | D5: =B5*Inputs!$D$6+C5*Inputs!$D$11 -> 0.0814 | E5: =B5*Inputs!$D$7+C5*Inputs!$D$12 -> 0.1226 | F5: =B5^2*Inputs!$D$7^2+C5^2*Inputs!$D$12^2+2*B5*C5*Inputs!$D$7*Inputs!$D$12*Inputs!$D$15 -> 0.01420756 | G5: =SQRT(F5) -> 0.11919547 | H5: =E5-G5 -> 0.0034045303 | I5: =IFERROR((D5-Inputs!$D$22)/G5,"") -> 0.26343283 | J5: =IF(D5>=INDEX($D$3:$D$103,MATCH(MIN($G$3:$G$103),$G$3:$G$103,0)),G5,NA()) -> #N/A | K5: =IF(D5>=INDEX($D$3:$D$103,MATCH(MIN($G$3:$G$103),$G$3:$G$103,0)),D5,NA()) -> #N/A | L5: =G5 -> 0.11919547 | M5: =D5 -> 0.0814 | N5: =IF(ABS(G5-MIN($G$3:$G$103))<0.00001,"★ MVP","")
A6: 4 | B6: =(ROW()-3)*0.01 -> 0.03 | C6: =1-B6 -> 0.97 | D6: =B6*Inputs!$D$6+C6*Inputs!$D$11 -> 0.0821 | E6: =B6*Inputs!$D$7+C6*Inputs!$D$12 -> 0.1239 | F6: =B6^2*Inputs!$D$7^2+C6^2*Inputs!$D$12^2+2*B6*C6*Inputs!$D$7*Inputs!$D$12*Inputs!$D$15 -> 0.01412901 | G6: =SQRT(F6) -> 0.11886551 | H6: =E6-G6 -> 0.0050344878 | I6: =IFERROR((D6-Inputs!$D$22)/G6,"") -> 0.2700531 | J6: =IF(D6>=INDEX($D$3:$D$103,MATCH(MIN($G$3:$G$103),$G$3:$G$103,0)),G6,NA()) -> #N/A | K6: =IF(D6>=INDEX($D$3:$D$103,MATCH(MIN($G$3:$G$103),$G$3:$G$103,0)),D6,NA()) -> #N/A | L6: =G6 -> 0.11886551 | M6: =D6 -> 0.0821 | N6: =IF(ABS(G6-MIN($G$3:$G$103))<0.00001,"★ MVP","")
A7: 5 | B7: =(ROW()-3)*0.01 -> 0.04 | C7: =1-B7 -> 0.96 | D7: =B7*Inputs!$D$6+C7*Inputs!$D$11 -> 0.0828 | E7: =B7*Inputs!$D$7+C7*Inputs!$D$12 -> 0.1252 | F7: =B7^2*Inputs!$D$7^2+C7^2*Inputs!$D$12^2+2*B7*C7*Inputs!$D$7*Inputs!$D$12*Inputs!$D$15 -> 0.01406224 | G7: =SQRT(F7) -> 0.11858432 | H7: =E7-G7 -> 0.006615684 | I7: =IFERROR((D7-Inputs!$D$22)/G7,"") -> 0.27659644 | J7: =IF(D7>=INDEX($D$3:$D$103,MATCH(MIN($G$3:$G$103),$G$3:$G$103,0)),G7,NA()) -> #N/A | K7: =IF(D7>=INDEX($D$3:$D$103,MATCH(MIN($G$3:$G$103),$G$3:$G$103,0)),D7,NA()) -> #N/A | L7: =G7 -> 0.11858432 | M7: =D7 -> 0.0828 | N7: =IF(ABS(G7-MIN($G$3:$G$103))<0.00001,"★ MVP","")
A8: 6 | B8: =(ROW()-3)*0.01 -> 0.05 | C8: =1-B8 -> 0.95 | D8: =B8*Inputs!$D$6+C8*Inputs!$D$11 -> 0.0835 | E8: =B8*Inputs!$D$7+C8*Inputs!$D$12 -> 0.1265 | F8: =B8^2*Inputs!$D$7^2+C8^2*Inputs!$D$12^2+2*B8*C8*Inputs!$D$7*Inputs!$D$12*Inputs!$D$15 -> 0.01400725 | G8: =SQRT(F8) -> 0.11835223 | H8: =E8-G8 -> 0.0081477715 | I8: =IFERROR((D8-Inputs!$D$22)/G8,"") -> 0.28305339 | J8: =IF(D8>=INDEX($D$3:$D$103,MATCH(MIN($G$3:$G$103),$G$3:$G$103,0)),G8,NA()) -> #N/A | K8: =IF(D8>=INDEX($D$3:$D$103,MATCH(MIN($G$3:$G$103),$G$3:$G$103,0)),D8,NA()) -> #N/A | L8: =G8 -> 0.11835223 | M8: =D8 -> 0.0835 | N8: =IF(ABS(G8-MIN($G$3:$G$103))<0.00001,"★ MVP","")
A9: 7 | B9: =(ROW()-3)*0.01 -> 0.06 | C9: =1-B9 -> 0.94 | D9: =B9*Inputs!$D$6+C9*Inputs!$D$11 -> 0.0842 | E9: =B9*Inputs!$D$7+C9*Inputs!$D$12 -> 0.1278 | F9: =B9^2*Inputs!$D$7^2+C9^2*Inputs!$D$12^2+2*B9*C9*Inputs!$D$7*Inputs!$D$12*Inputs!$D$15 -> 0.01396404 | G9: =SQRT(F9) -> 0.11816954 | H9: =E9-G9 -> 0.0096304608 | I9: =IFERROR((D9-Inputs!$D$22)/G9,"") -> 0.28941469 | J9: =IF(D9>=INDEX($D$3:$D$103,MATCH(MIN($G$3:$G$103),$G$3:$G$103,0)),G9,NA()) -> #N/A | K9: =IF(D9>=INDEX($D$3:$D$103,MATCH(MIN($G$3:$G$103),$G$3:$G$103,0)),D9,NA()) -> #N/A | L9: =G9 -> 0.11816954 | M9: =D9 -> 0.0842 | N9: =IF(ABS(G9-MIN($G$3:$G$103))<0.00001,"★ MVP","")
A10: 8 | B10: =(ROW()-3)*0.01 -> 0.07 | C10: =1-B10 -> 0.93 | D10: =B10*Inputs!$D$6+C10*Inputs!$D$11 -> 0.0849 | E10: =B10*Inputs!$D$7+C10*Inputs!$D$12 -> 0.1291 | F10: =B10^2*Inputs!$D$7^2+C10^2*Inputs!$D$12^2+2*B10*C10*Inputs!$D$7*Inputs!$D$12*Inputs!$D$15 -> 0.01393261 | G10: =SQRT(F10) -> 0.11803648 | H10: =E10-G10 -> 0.011063523 | I10: =IFERROR((D10-Inputs!$D$22)/G10,"") -> 0.29567131 | J10: =IF(D10>=INDEX($D$3:$D$103,MATCH(MIN($G$3:$G$103),$G$3:$G$103,0)),G10,NA()) -> #N/A | K10: =IF(D10>=INDEX($D$3:$D$103,MATCH(MIN($G$3:$G$103),$G$3:$G$103,0)),D10,NA()) -> #N/A | L10: =G10 -> 0.11803648 | M10: =D10 -> 0.0849 | N10: =IF(ABS(G10-MIN($G$3:$G$103))<0.00001,"★ MVP","")
A11: 9 | B11: =(ROW()-3)*0.01 -> 0.08 | C11: =1-B11 -> 0.92 | D11: =B11*Inputs!$D$6+C11*Inputs!$D$11 -> 0.0856 | E11: =B11*Inputs!$D$7+C11*Inputs!$D$12 -> 0.1304 | F11: =B11^2*Inputs!$D$7^2+C11^2*Inputs!$D$12^2+2*B11*C11*Inputs!$D$7*Inputs!$D$12*Inputs!$D$15 -> 0.01391296 | G11: =SQRT(F11) -> 0.11795321 | H11: =E11-G11 -> 0.012446789 | I11: =IFERROR((D11-Inputs!$D$22)/G11,"") -> 0.30181459 | J11: =IF(D11>=INDEX($D$3:$D$103,MATCH(MIN($G$3:$G$103),$G$3:$G$103,0)),G11,NA()) -> #N/A | K11: =IF(D11>=INDEX($D$3:$D$103,MATCH(MIN($G$3:$G$103),$G$3:$G$103,0)),D11,NA()) -> #N/A | L11: =G11 -> 0.11795321 | M11: =D11 -> 0.0856 | N11: =IF(ABS(G11-MIN($G$3:$G$103))<0.00001,"★ MVP","")
A12: 10 | B12: =(ROW()-3)*0.01 -> 0.09 | C12: =1-B12 -> 0.91 | D12: =B12*Inputs!$D$6+C12*Inputs!$D$11 -> 0.0863 | E12: =B12*Inputs!$D$7+C12*Inputs!$D$12 -> 0.1317 | F12: =B12^2*Inputs!$D$7^2+C12^2*Inputs!$D$12^2+2*B12*C12*Inputs!$D$7*Inputs!$D$12*Inputs!$D$15 -> 0.01390509 | G12: =SQRT(F12) -> 0.11791985 | H12: =E12-G12 -> 0.013780154 | I12: =IFERROR((D12-Inputs!$D$22)/G12,"") -> 0.30783622 | J12: =IF(D12>=INDEX($D$3:$D$103,MATCH(MIN($G$3:$G$103),$G$3:$G$103,0)),G12,NA()) -> 0.11791985 | K12: =IF(D12>=INDEX($D$3:$D$103,MATCH(MIN($G$3:$G$103),$G$3:$G$103,0)),D12,NA()) -> 0.0863 | L12: =G12 -> 0.11791985 | M12: =D12 -> 0.0863 | N12: =IF(ABS(G12-MIN($G$3:$G$103))<0.00001,"★ MVP","") -> ★ MVP
A13: 11 | B13: =(ROW()-3)*0.01 -> 0.1 | C13: =1-B13 -> 0.9 | D13: =B13*Inputs!$D$6+C13*Inputs!$D$11 -> 0.087 | E13: =B13*Inputs!$D$7+C13*Inputs!$D$12 -> 0.133 | F13: =B13^2*Inputs!$D$7^2+C13^2*Inputs!$D$12^2+2*B13*C13*Inputs!$D$7*Inputs!$D$12*Inputs!$D$15 -> 0.013909 | G13: =SQRT(F13) -> 0.11793642 | H13: =E13-G13 -> 0.015063576 | I13: =IFERROR((D13-Inputs!$D$22)/G13,"") -> 0.31372835 | J13: =IF(D13>=INDEX($D$3:$D$103,MATCH(MIN($G$3:$G$103),$G$3:$G$103,0)),G13,NA()) -> 0.11793642 | K13: =IF(D13>=INDEX($D$3:$D$103,MATCH(MIN($G$3:$G$103),$G$3:$G$103,0)),D13,NA()) -> 0.087 | L13: =G13 -> 0.11793642 | M13: =D13 -> 0.087 | N13: =IF(ABS(G13-MIN($G$3:$G$103))<0.00001,"★ MVP","")
A14: 12 | B14: =(ROW()-3)*0.01 -> 0.11 | C14: =1-B14 -> 0.89 | D14: =B14*Inputs!$D$6+C14*Inputs!$D$11 -> 0.0877 | E14: =B14*Inputs!$D$7+C14*Inputs!$D$12 -> 0.1343 | F14: =B14^2*Inputs!$D$7^2+C14^2*Inputs!$D$12^2+2*B14*C14*Inputs!$D$7*Inputs!$D$12*Inputs!$D$15 -> 0.01392469 | G14: =SQRT(F14) -> 0.11800292 | H14: =E14-G14 -> 0.016297076 | I14: =IFERROR((D14-Inputs!$D$22)/G14,"") -> 0.31948361 | J14: =IF(D14>=INDEX($D$3:$D$103,MATCH(MIN($G$3:$G$103),$G$3:$G$103,0)),G14,NA()) -> 0.11800292 | K14: =IF(D14>=INDEX($D$3:$D$103,MATCH(MIN($G$3:$G$103),$G$3:$G$103,0)),D14,NA()) -> 0.0877 | L14: =G14 -> 0.11800292 | M14: =D14 -> 0.0877 | N14: =IF(ABS(G14-MIN($G$3:$G$103))<0.00001,"★ MVP","")
... A103: 101 | B103: =(ROW()-3)*0.01 -> 1 | C103: =1-B103 -> 0 | D103: =B103*Inputs!$D$6+C103*Inputs!$D$11 -> 0.15 | E103: =B103*Inputs!$D$7+C103*Inputs!$D$12 -> 0.25 | F103: =B103^2*Inputs!$D$7^2+C103^2*Inputs!$D$12^2+2*B103*C103*Inputs!$D$7*Inputs!$D$12*Inputs!$D$15 -> 0.0625 | G103: =SQRT(F103) -> 0.25 | H103: =E103-G103 -> 0 | I103: =IFERROR((D103-Inputs!$D$22)/G103,"") -> 0.4 | J103: =IF(D103>=INDEX($D$3:$D$103,MATCH(MIN($G$3:$G$103),$G$3:$G$103,0)),G103,NA()) -> 0.25 | K103: =IF(D103>=INDEX($D$3:$D$103,MATCH(MIN($G$3:$G$103),$G$3:$G$103,0)),D103,NA()) -> 0.15 | L103: =G103 -> 0.25 | M103: =D103 -> 0.15 | N103: =IF(ABS(G103-MIN($G$3:$G$103))<0.00001,"★ MVP","")
P105: Point Label | Q105: Std Dev X | R105: Return Y
P106: Asset A (100% in A) | Q106: =G103 -> 0.25 | R106: =D103 -> 0.15
P107: Asset B (100% in B) | Q107: =G3 -> 0.12 | R107: =D3 -> 0.08
P108: Min Variance Portfolio | Q108: =MIN($G$3:$G$103) -> 0.11791985 | R108: =INDEX($D$3:$D$103,MATCH(MIN($G$3:$G$103),$G$3:$G$103,0)) -> 0.0863

Sheet Efficient Frontier Chart
A1: EFFICIENT FRONTIER CHART — Two-Asset Portfolio Opportunity Set
A2: This XY Scatter chart shows: (1) Full Opportunity Set [gray] — all 101 portfolios, (2) Efficient Frontier [navy] — from MVP upward, (3) MVP [red diamond], (4) Asset A [green circle], (5) Asset B [orange square]. Change Correlation on the Inputs sheet to see the curve shift live.
A32: KEY CHART NOTES: • X-axis = Portfolio Standard Deviation σp (risk). Y-axis = Expected Return E(Rp). • The full parabola (gray) is the Opportunity Set — all possible risk-return combinations. • The EFFICIENT FRONTIER (navy) = upper portion from MVP to Asset A. These are not dominated. • Portfolios below the MVP (lower arc) are DOMINATED — same risk, lower return. • Change ρ on Inputs sheet to see: ρ = +1 gives a straight line; ρ < +1 gives a curve.

Sheet Correlation Demonstration
A1: HOW CORRELATION SHAPES THE OPPORTUNITY SET — Five Curves Comparison
A2: # | B2: wA | C2: wB | D2: E(Rp) | E2: σp (ρ = +1.00) | F2: σp (ρ = +0.50) | G2: σp (ρ = 0.00) | H2: σp (ρ = –0.50) | I2: σp (ρ = –1.00)
A3: 1 | B3: =(ROW()-3)*0.01 -> 0 | C3: =1-B3 -> 1 | D3: =B3*Inputs!$D$6+C3*Inputs!$D$11 -> 0.08 | E3: =SQRT(B3^2*Inputs!$D$7^2+C3^2*Inputs!$D$12^2+2*B3*C3*Inputs!$D$7*Inputs!$D$12*1) -> 0.12 | F3: =SQRT(B3^2*Inputs!$D$7^2+C3^2*Inputs!$D$12^2+2*B3*C3*Inputs!$D$7*Inputs!$D$12*0.5) -> 0.12 | G3: =SQRT(B3^2*Inputs!$D$7^2+C3^2*Inputs!$D$12^2+2*B3*C3*Inputs!$D$7*Inputs!$D$12*0) -> 0.12 | H3: =SQRT(B3^2*Inputs!$D$7^2+C3^2*Inputs!$D$12^2+2*B3*C3*Inputs!$D$7*Inputs!$D$12*-0.5) -> 0.12 | I3: =SQRT(B3^2*Inputs!$D$7^2+C3^2*Inputs!$D$12^2+2*B3*C3*Inputs!$D$7*Inputs!$D$12*-1) -> 0.12
A4: 2 | B4: =(ROW()-3)*0.01 -> 0.01 | C4: =1-B4 -> 0.99 | D4: =B4*Inputs!$D$6+C4*Inputs!$D$11 -> 0.0807 | E4: =SQRT(B4^2*Inputs!$D$7^2+C4^2*Inputs!$D$12^2+2*B4*C4*Inputs!$D$7*Inputs!$D$12*1) -> 0.1213 | F4: =SQRT(B4^2*Inputs!$D$7^2+C4^2*Inputs!$D$12^2+2*B4*C4*Inputs!$D$7*Inputs!$D$12*0.5) -> 0.12006952 | G4: =SQRT(B4^2*Inputs!$D$7^2+C4^2*Inputs!$D$12^2+2*B4*C4*Inputs!$D$7*Inputs!$D$12*0) -> 0.1188263 | H4: =SQRT(B4^2*Inputs!$D$7^2+C4^2*Inputs!$D$12^2+2*B4*C4*Inputs!$D$7*Inputs!$D$12*-0.5) -> 0.11756994 | I4: =SQRT(B4^2*Inputs!$D$7^2+C4^2*Inputs!$D$12^2+2*B4*C4*Inputs!$D$7*Inputs!$D$12*-1) -> 0.1163
A5: 3 | B5: =(ROW()-3)*0.01 -> 0.02 | C5: =1-B5 -> 0.98 | D5: =B5*Inputs!$D$6+C5*Inputs!$D$11 -> 0.0814 | E5: =SQRT(B5^2*Inputs!$D$7^2+C5^2*Inputs!$D$12^2+2*B5*C5*Inputs!$D$7*Inputs!$D$12*1) -> 0.1226 | F5: =SQRT(B5^2*Inputs!$D$7^2+C5^2*Inputs!$D$12^2+2*B5*C5*Inputs!$D$7*Inputs!$D$12*0.5) -> 0.12017803 | G5: =SQRT(B5^2*Inputs!$D$7^2+C5^2*Inputs!$D$12^2+2*B5*C5*Inputs!$D$7*Inputs!$D$12*0) -> 0.11770624 | H5: =SQRT(B5^2*Inputs!$D$7^2+C5^2*Inputs!$D$12^2+2*B5*C5*Inputs!$D$7*Inputs!$D$12*-0.5) -> 0.11518142 | I5: =SQRT(B5^2*Inputs!$D$7^2+C5^2*Inputs!$D$12^2+2*B5*C5*Inputs!$D$7*Inputs!$D$12*-1) -> 0.1126
A6: 4 | B6: =(ROW()-3)*0.01 -> 0.03 | C6: =1-B6 -> 0.97 | D6: =B6*Inputs!$D$6+C6*Inputs!$D$11 -> 0.0821 | E6: =SQRT(B6^2*Inputs!$D$7^2+C6^2*Inputs!$D$12^2+2*B6*C6*Inputs!$D$7*Inputs!$D$12*1) -> 0.1239 | F6: =SQRT(B6^2*Inputs!$D$7^2+C6^2*Inputs!$D$12^2+2*B6*C6*Inputs!$D$7*Inputs!$D$12*0.5) -> 0.12032543 | G6: =SQRT(B6^2*Inputs!$D$7^2+C6^2*Inputs!$D$12^2+2*B6*C6*Inputs!$D$7*Inputs!$D$12*0) -> 0.11664137 | H6: =SQRT(B6^2*Inputs!$D$7^2+C6^2*Inputs!$D$12^2+2*B6*C6*Inputs!$D$7*Inputs!$D$12*-0.5) -> 0.11283709 | I6: =SQRT(B6^2*Inputs!$D$7^2+C6^2*Inputs!$D$12^2+2*B6*C6*Inputs!$D$7*Inputs!$D$12*-1) -> 0.1089
A7: 5 | B7: =(ROW()-3)*0.01 -> 0.04 | C7: =1-B7 -> 0.96 | D7: =B7*Inputs!$D$6+C7*Inputs!$D$11 -> 0.0828 | E7: =SQRT(B7^2*Inputs!$D$7^2+C7^2*Inputs!$D$12^2+2*B7*C7*Inputs!$D$7*Inputs!$D$12*1) -> 0.1252 | F7: =SQRT(B7^2*Inputs!$D$7^2+C7^2*Inputs!$D$12^2+2*B7*C7*Inputs!$D$7*Inputs!$D$12*0.5) -> 0.12051158 | G7: =SQRT(B7^2*Inputs!$D$7^2+C7^2*Inputs!$D$12^2+2*B7*C7*Inputs!$D$7*Inputs!$D$12*0) -> 0.11563321 | H7: =SQRT(B7^2*Inputs!$D$7^2+C7^2*Inputs!$D$12^2+2*B7*C7*Inputs!$D$7*Inputs!$D$12*-0.5) -> 0.11053977 | I7: =SQRT(B7^2*Inputs!$D$7^2+C7^2*Inputs!$D$12^2+2*B7*C7*Inputs!$D$7*Inputs!$D$12*-1) -> 0.1052
A8: 6 | B8: =(ROW()-3)*0.01 -> 0.05 | C8: =1-B8 -> 0.95 | D8: =B8*Inputs!$D$6+C8*Inputs!$D$11 -> 0.0835 | E8: =SQRT(B8^2*Inputs!$D$7^2+C8^2*Inputs!$D$12^2+2*B8*C8*Inputs!$D$7*Inputs!$D$12*1) -> 0.1265 | F8: =SQRT(B8^2*Inputs!$D$7^2+C8^2*Inputs!$D$12^2+2*B8*C8*Inputs!$D$7*Inputs!$D$12*0.5) -> 0.12073628 | G8: =SQRT(B8^2*Inputs!$D$7^2+C8^2*Inputs!$D$12^2+2*B8*C8*Inputs!$D$7*Inputs!$D$12*0) -> 0.11468326 | H8: =SQRT(B8^2*Inputs!$D$7^2+C8^2*Inputs!$D$12^2+2*B8*C8*Inputs!$D$7*Inputs!$D$12*-0.5) -> 0.10829243 | I8: =SQRT(B8^2*Inputs!$D$7^2+C8^2*Inputs!$D$12^2+2*B8*C8*Inputs!$D$7*Inputs!$D$12*-1) -> 0.1015
A9: 7 | B9: =(ROW()-3)*0.01 -> 0.06 | C9: =1-B9 -> 0.94 | D9: =B9*Inputs!$D$6+C9*Inputs!$D$11 -> 0.0842 | E9: =SQRT(B9^2*Inputs!$D$7^2+C9^2*Inputs!$D$12^2+2*B9*C9*Inputs!$D$7*Inputs!$D$12*1) -> 0.1278 | F9: =SQRT(B9^2*Inputs!$D$7^2+C9^2*Inputs!$D$12^2+2*B9*C9*Inputs!$D$7*Inputs!$D$12*0.5) -> 0.12099934 | G9: =SQRT(B9^2*Inputs!$D$7^2+C9^2*Inputs!$D$12^2+2*B9*C9*Inputs!$D$7*Inputs!$D$12*0) -> 0.11379297 | H9: =SQRT(B9^2*Inputs!$D$7^2+C9^2*Inputs!$D$12^2+2*B9*C9*Inputs!$D$7*Inputs!$D$12*-0.5) -> 0.10609826 | I9: =SQRT(B9^2*Inputs!$D$7^2+C9^2*Inputs!$D$12^2+2*B9*C9*Inputs!$D$7*Inputs!$D$12*-1) -> 0.0978
A10: 8 | B10: =(ROW()-3)*0.01 -> 0.07 | C10: =1-B10 -> 0.93 | D10: =B10*Inputs!$D$6+C10*Inputs!$D$11 -> 0.0849 | E10: =SQRT(B10^2*Inputs!$D$7^2+C10^2*Inputs!$D$12^2+2*B10*C10*Inputs!$D$7*Inputs!$D$12*1) -> 0.1291 | F10: =SQRT(B10^2*Inputs!$D$7^2+C10^2*Inputs!$D$12^2+2*B10*C10*Inputs!$D$7*Inputs!$D$12*0.5) -> 0.12130049 | G10: =SQRT(B10^2*Inputs!$D$7^2+C10^2*Inputs!$D$12^2+2*B10*C10*Inputs!$D$7*Inputs!$D$12*0) -> 0.11296376 | H10: =SQRT(B10^2*Inputs!$D$7^2+C10^2*Inputs!$D$12^2+2*B10*C10*Inputs!$D$7*Inputs!$D$12*-0.5) -> 0.10396062 | I10: =SQRT(B10^2*Inputs!$D$7^2+C10^2*Inputs!$D$12^2+2*B10*C10*Inputs!$D$7*Inputs!$D$12*-1) -> 0.0941
A11: 9 | B11: =(ROW()-3)*0.01 -> 0.08 | C11: =1-B11 -> 0.92 | D11: =B11*Inputs!$D$6+C11*Inputs!$D$11 -> 0.0856 | E11: =SQRT(B11^2*Inputs!$D$7^2+C11^2*Inputs!$D$12^2+2*B11*C11*Inputs!$D$7*Inputs!$D$12*1) -> 0.1304 | F11: =SQRT(B11^2*Inputs!$D$7^2+C11^2*Inputs!$D$12^2+2*B11*C11*Inputs!$D$7*Inputs!$D$12*0.5) -> 0.12163947 | G11: =SQRT(B11^2*Inputs!$D$7^2+C11^2*Inputs!$D$12^2+2*B11*C11*Inputs!$D$7*Inputs!$D$12*0) -> 0.11219697 | H11: =SQRT(B11^2*Inputs!$D$7^2+C11^2*Inputs!$D$12^2+2*B11*C11*Inputs!$D$7*Inputs!$D$12*-0.5) -> 0.10188307 | I11: =SQRT(B11^2*Inputs!$D$7^2+C11^2*Inputs!$D$12^2+2*B11*C11*Inputs!$D$7*Inputs!$D$12*-1) -> 0.0904
A12: 10 | B12: =(ROW()-3)*0.01 -> 0.09 | C12: =1-B12 -> 0.91 | D12: =B12*Inputs!$D$6+C12*Inputs!$D$11 -> 0.0863 | E12: =SQRT(B12^2*Inputs!$D$7^2+C12^2*Inputs!$D$12^2+2*B12*C12*Inputs!$D$7*Inputs!$D$12*1) -> 0.1317 | F12: =SQRT(B12^2*Inputs!$D$7^2+C12^2*Inputs!$D$12^2+2*B12*C12*Inputs!$D$7*Inputs!$D$12*0.5) -> 0.12201594 | G12: =SQRT(B12^2*Inputs!$D$7^2+C12^2*Inputs!$D$12^2+2*B12*C12*Inputs!$D$7*Inputs!$D$12*0) -> 0.1114939 | H12: =SQRT(B12^2*Inputs!$D$7^2+C12^2*Inputs!$D$12^2+2*B12*C12*Inputs!$D$7*Inputs!$D$12*-0.5) -> 0.099869365 | I12: =SQRT(B12^2*Inputs!$D$7^2+C12^2*Inputs!$D$12^2+2*B12*C12*Inputs!$D$7*Inputs!$D$12*-1) -> 0.0867
A13: 11 | B13: =(ROW()-3)*0.01 -> 0.1 | C13: =1-B13 -> 0.9 | D13: =B13*Inputs!$D$6+C13*Inputs!$D$11 -> 0.087 | E13: =SQRT(B13^2*Inputs!$D$7^2+C13^2*Inputs!$D$12^2+2*B13*C13*Inputs!$D$7*Inputs!$D$12*1) -> 0.133 | F13: =SQRT(B13^2*Inputs!$D$7^2+C13^2*Inputs!$D$12^2+2*B13*C13*Inputs!$D$7*Inputs!$D$12*0.5) -> 0.12242957 | G13: =SQRT(B13^2*Inputs!$D$7^2+C13^2*Inputs!$D$12^2+2*B13*C13*Inputs!$D$7*Inputs!$D$12*0) -> 0.11085576 | H13: =SQRT(B13^2*Inputs!$D$7^2+C13^2*Inputs!$D$12^2+2*B13*C13*Inputs!$D$7*Inputs!$D$12*-0.5) -> 0.097923439 | I13: =SQRT(B13^2*Inputs!$D$7^2+C13^2*Inputs!$D$12^2+2*B13*C13*Inputs!$D$7*Inputs!$D$12*-1) -> 0.083
A14: 12 | B14: =(ROW()-3)*0.01 -> 0.11 | C14: =1-B14 -> 0.89 | D14: =B14*Inputs!$D$6+C14*Inputs!$D$11 -> 0.0877 | E14: =SQRT(B14^2*Inputs!$D$7^2+C14^2*Inputs!$D$12^2+2*B14*C14*Inputs!$D$7*Inputs!$D$12*1) -> 0.1343 | F14: =SQRT(B14^2*Inputs!$D$7^2+C14^2*Inputs!$D$12^2+2*B14*C14*Inputs!$D$7*Inputs!$D$12*0.5) -> 0.12287998 | G14: =SQRT(B14^2*Inputs!$D$7^2+C14^2*Inputs!$D$12^2+2*B14*C14*Inputs!$D$7*Inputs!$D$12*0) -> 0.11028368 | H14: =SQRT(B14^2*Inputs!$D$7^2+C14^2*Inputs!$D$12^2+2*B14*C14*Inputs!$D$7*Inputs!$D$12*-0.5) -> 0.096049414 | I14: =SQRT(B14^2*Inputs!$D$7^2+C14^2*Inputs!$D$12^2+2*B14*C14*Inputs!$D$7*Inputs!$D$12*-1) -> 0.0793
... A103: 101 | B103: =(ROW()-3)*0.01 -> 1 | C103: =1-B103 -> 0 | D103: =B103*Inputs!$D$6+C103*Inputs!$D$11 -> 0.15 | E103: =SQRT(B103^2*Inputs!$D$7^2+C103^2*Inputs!$D$12^2+2*B103*C103*Inputs!$D$7*Inputs!$D$12*1) -> 0.25 | F103: =SQRT(B103^2*Inputs!$D$7^2+C103^2*Inputs!$D$12^2+2*B103*C103*Inputs!$D$7*Inputs!$D$12*0.5) -> 0.25 | G103: =SQRT(B103^2*Inputs!$D$7^2+C103^2*Inputs!$D$12^2+2*B103*C103*Inputs!$D$7*Inputs!$D$12*0) -> 0.25 | H103: =SQRT(B103^2*Inputs!$D$7^2+C103^2*Inputs!$D$12^2+2*B103*C103*Inputs!$D$7*Inputs!$D$12*-0.5) -> 0.25 | I103: =SQRT(B103^2*Inputs!$D$7^2+C103^2*Inputs!$D$12^2+2*B103*C103*Inputs!$D$7*Inputs!$D$12*-1) -> 0.25
A110: ρ = +1.00: No diversification benefit. The opportunity set collapses to a straight line. Adding Asset B does not reduce portfolio risk at all.
A112: ρ = +0.50: Partial diversification benefit. The frontier curves gently — some risk reduction when combining assets.
A114: ρ = 0.00: Strong diversification benefit. Assets move independently. Portfolio risk is noticeably below the weighted average.
A116: ρ = –0.50: Very strong diversification. The frontier curves significantly to the left — substantial risk reduction.
A118: ρ = –1.00: Perfect hedge. At the right weight combination, portfolio risk can theoretically reach zero.

Sheet Minimum Variance Portfolio
B1: MINIMUM VARIANCE PORTFOLIO (MVP) — ANALYTICAL SOLUTION
B3: I. Input Parameters (Linked from Inputs Sheet)
C4: Asset A – Expected Return E(RA) | D4: =Inputs!$D$6 -> 0.15
C5: Asset A – Standard Deviation σA | D5: =Inputs!$D$7 -> 0.25
C6: Asset B – Expected Return E(RB) | D6: =Inputs!$D$11 -> 0.08
C7: Asset B – Standard Deviation σB | D7: =Inputs!$D$12 -> 0.12
C8: Correlation ρAB | D8: =Inputs!$D$15 -> 0.3
B10: II. Covariance Calculation
C11: Covariance CovAB = ρAB × σA × σB | D11: =Inputs!$D$15*Inputs!$D$7*Inputs!$D$12 -> 0.009 | E11: Calc: ρAB × σA × σB
B13: III. Minimum Variance Portfolio Weights (Analytical Formula)
C14: Formula: wA* = (σB² – CovAB) / (σA² + σB² – 2 × CovAB)
C15: MVP Weight in Asset A (wA*) | D15: =(Inputs!$D$12^2-D11)/(Inputs!$D$7^2+Inputs!$D$12^2-2*D11) -> 0.091680815 | E15: Calc: (σB² – CovAB) / (σA² + σB² – 2×CovAB)
C16: MVP Weight in Asset B (wB*) | D16: =1-D15 -> 0.90831919 | E16: Calc: 1 – wA*
B18: IV. MVP Portfolio Statistics
C19: Expected Return E(Rp_MVP) | D19: =D15*D4+D16*D6 -> 0.086417657
C20: Portfolio Variance σp² | D20: =D15^2*D5^2+D16^2*D7^2+2*D15*D16*D11 -> 0.013904924
C21: Portfolio Std Dev σp_MVP | D21: =SQRT(D20) -> 0.11791914
C22: Sharpe Ratio (MVP) | D22: =(D19-Inputs!$D$22)/D21 -> 0.30883584
B24: V. Cross-Check: Analytical MVP vs. Numerical Table
C25: Minimum σp from 101-portfolio table | D25: =MIN('Two-Asset Frontier Calculations'!$G$3:$G$103) -> 0.11791985 | E25: =MIN('Two-Asset Frontier Calculations'!G3:G103) -> 0.11791985
C26: Return at minimum σp (from table) | D26: =INDEX('Two-Asset Frontier Calculations'!$D$3:$D$103,MATCH(MIN('Two-Asset Frontier Calculations'!$G$3:$G$103),'Two-Asset Frontier Calculations'!$G$3:$G$103,0)) -> 0.0863 | E26: Should match D19 above
C27: Difference (Analytical Std Dev – Table Std Dev) | D27: =D21-D25 -> -7.0556901e-07 | E27: ≈ 0 (tiny rounding diff between 1% step table & exact formula)
B29: KEY INSIGHT: The MVP minimises portfolio risk for the given assets and correlation. It is NOT necessarily the optimal portfolio for every investor. A risk-averse investor may prefer MVP; a growth-oriented investor may prefer a higher point on the Efficient Frontier. The MVP is simply the leftmost point of the opportunity set — the starting point of the Efficient Frontier.

Sheet Capital Market Line
B1: CAPITAL MARKET LINE (CML) — Introducing the Risk-Free Asset
B3: I. Tangency Portfolio (Maximum Sharpe Ratio Portfolio from the Two-Asset Frontier)
C4: Maximum Sharpe Ratio (= Tangency Portfolio Sharpe) | D4: =MAX('Two-Asset Frontier Calculations'!$I$3:$I$103) -> 0.4225719
C5: Tangency Portfolio: Weight in Asset A | D5: =INDEX('Two-Asset Frontier Calculations'!$B$3:$B$103,MATCH(MAX('Two-Asset Frontier Calculations'!$I$3:$I$103),'Two-Asset Frontier Calculations'!$I$3:$I$103,0)) -> 0.55
C6: Tangency Portfolio: Weight in Asset B | D6: =1-D5 -> 0.45
C7: Tangency Portfolio: Expected Return E(RT) | D7: =D5*Inputs!$D$6+(1-D5)*Inputs!$D$11 -> 0.1185
C8: Tangency Portfolio: Std Dev σT | D8: =INDEX('Two-Asset Frontier Calculations'!$G$3:$G$103,MATCH(MAX('Two-Asset Frontier Calculations'!$I$3:$I$103),'Two-Asset Frontier Calculations'!$I$3:$I$103,0)) -> 0.16210259
C9: CML Slope = (E(RT) – Rf) / σT | D9: =(D7-Inputs!$D$22)/D8 -> 0.4225719
C10: Risk-Free Rate Rf | D10: =Inputs!$D$22 -> 0.05
B12: CML FORMULA: E(Rp) = Rf + [(E(RT) – Rf) / σT] × σp = Rf + Sharpe_T × σp The CML slope equals the Tangency Portfolio Sharpe Ratio. Every point on the CML is a mix of the risk-free asset and the Tangency Portfolio. • wT < 100%: Lending portfolio (hold some Rf + some Tangency) • wT = 100%: Tangency Portfolio • wT > 100%: Leveraged / Borrowing portfolio (borrow at Rf to buy more Tangency)
B14: II. CML Allocation Table (wT from 0% to 150%)
F15: wT (Tangency) | G15: wRF (Risk-Free) | H15: Portfolio Return | I15: Portfolio Risk σp | J15: Region
F16: 0 | G16: =1-F16 -> 1 | H16: =Inputs!$D$22+F16*(D7-Inputs!$D$22) -> 0.05 | I16: =F16*D8 -> 0 | J16: Lending Portfolio
F17: =F16+0.1 -> 0.1 | G17: =1-F17 -> 0.9 | H17: =Inputs!$D$22+F17*(D7-Inputs!$D$22) -> 0.05685 | I17: =F17*D8 -> 0.016210259 | J17: Lending Portfolio
F18: =F17+0.1 -> 0.2 | G18: =1-F18 -> 0.8 | H18: =Inputs!$D$22+F18*(D7-Inputs!$D$22) -> 0.0637 | I18: =F18*D8 -> 0.032420518 | J18: Lending Portfolio
F19: =F18+0.1 -> 0.3 | G19: =1-F19 -> 0.7 | H19: =Inputs!$D$22+F19*(D7-Inputs!$D$22) -> 0.07055 | I19: =F19*D8 -> 0.048630777 | J19: Lending Portfolio
F20: =F19+0.1 -> 0.4 | G20: =1-F20 -> 0.6 | H20: =Inputs!$D$22+F20*(D7-Inputs!$D$22) -> 0.0774 | I20: =F20*D8 -> 0.064841036 | J20: Lending Portfolio
F21: =F20+0.1 -> 0.5 | G21: =1-F21 -> 0.5 | H21: =Inputs!$D$22+F21*(D7-Inputs!$D$22) -> 0.08425 | I21: =F21*D8 -> 0.081051295 | J21: Lending Portfolio
F22: =F21+0.1 -> 0.6 | G22: =1-F22 -> 0.4 | H22: =Inputs!$D$22+F22*(D7-Inputs!$D$22) -> 0.0911 | I22: =F22*D8 -> 0.097261555 | J22: Lending Portfolio
F23: =F22+0.1 -> 0.7 | G23: =1-F23 -> 0.3 | H23: =Inputs!$D$22+F23*(D7-Inputs!$D$22) -> 0.09795 | I23: =F23*D8 -> 0.11347181 | J23: Lending Portfolio
F24: =F23+0.1 -> 0.8 | G24: =1-F24 -> 0.2 | H24: =Inputs!$D$22+F24*(D7-Inputs!$D$22) -> 0.1048 | I24: =F24*D8 -> 0.12968207 | J24: Lending Portfolio
F25: =F24+0.1 -> 0.9 | G25: =1-F25 -> 0.1 | H25: =Inputs!$D$22+F25*(D7-Inputs!$D$22) -> 0.11165 | I25: =F25*D8 -> 0.14589233 | J25: Lending Portfolio
F26: =F25+0.1 -> 1 | G26: =1-F26 -> 0 | H26: =Inputs!$D$22+F26*(D7-Inputs!$D$22) -> 0.1185 | I26: =F26*D8 -> 0.16210259 | J26: ★ Tangency Portfolio
F27: =F26+0.1 -> 1.1 | G27: =1-F27 -> -0.1 | H27: =Inputs!$D$22+F27*(D7-Inputs!$D$22) -> 0.12535 | I27: =F27*D8 -> 0.17831285 | J27: Leveraged / Borrowing
F28: =F27+0.1 -> 1.2 | G28: =1-F28 -> -0.2 | H28: =Inputs!$D$22+F28*(D7-Inputs!$D$22) -> 0.1322 | I28: =F28*D8 -> 0.19452311 | J28: Leveraged / Borrowing
F29: =F28+0.1 -> 1.3 | G29: =1-F29 -> -0.3 | H29: =Inputs!$D$22+F29*(D7-Inputs!$D$22) -> 0.13905 | I29: =F29*D8 -> 0.21073337 | J29: Leveraged / Borrowing
F30: =F29+0.1 -> 1.4 | G30: =1-F30 -> -0.4 | H30: =Inputs!$D$22+F30*(D7-Inputs!$D$22) -> 0.1459 | I30: =F30*D8 -> 0.22694363 | J30: Leveraged / Borrowing
F31: =F30+0.1 -> 1.5 | G31: =1-F31 -> -0.5 | H31: =Inputs!$D$22+F31*(D7-Inputs!$D$22) -> 0.15275 | I31: =F31*D8 -> 0.24315389 | J31: Leveraged / Borrowing
I33: Risk-Free Asset (σ=0): | J33: 0 | K33: =Inputs!$D$22 -> 0.05

Sheet CAPM Calculator
B1: CAPM CALCULATOR — Required Return = Rf + β × (E(Rm) – Rf)
B3: Market Parameters (Linked from Inputs Sheet)
C4: Risk-Free Rate Rf | D4: =Inputs!$D$22 -> 0.05
C5: Expected Market Return E(Rm) | D5: =Inputs!$D$23 -> 0.12
C6: Market Risk Premium = E(Rm) – Rf | D6: =Inputs!$D$23-Inputs!$D$22 -> 0.07
B8: CAPM Required Returns by Beta
C9: Beta β | D9: Risk Classification | E9: Required Return E(Ri) | F9: Interpretation
C10: 0.5 | D10: Defensive (β < 1) | E10: =Inputs!$D$22+0.5*(Inputs!$D$23-Inputs!$D$22) -> 0.085 | F10: Half the market sensitivity — low-risk, defensive stock
C11: 0.75 | D11: Defensive (β < 1) | E11: =Inputs!$D$22+0.75*(Inputs!$D$23-Inputs!$D$22) -> 0.1025 | F11: 75% of market risk — near-defensive
C12: 1 | D12: Market Risk (β = 1) | E12: =Inputs!$D$22+1*(Inputs!$D$23-Inputs!$D$22) -> 0.12 | F12: Exactly market risk — moves 1:1 with market
C13: 1.25 | D13: Aggressive (β > 1) | E13: =Inputs!$D$22+1.25*(Inputs!$D$23-Inputs!$D$22) -> 0.1375 | F13: 25% more sensitive than market
C14: 1.5 | D14: Aggressive (β > 1) | E14: =Inputs!$D$22+1.5*(Inputs!$D$23-Inputs!$D$22) -> 0.155 | F14: 50% more volatile than market
C15: 2 | D15: Aggressive (β > 1) | E15: =Inputs!$D$22+2*(Inputs!$D$23-Inputs!$D$22) -> 0.19 | F15: Twice as volatile as market — high systematic risk
B17: CAPM FORMULA: E(Ri) = Rf + βi × [E(Rm) – Rf] • βi < 1 → Defensive: required return < market return (lower systematic risk) • βi = 1 → Market portfolio: required return = market return • βi > 1 → Aggressive: required return > market return (higher systematic risk) CRITICAL INSIGHT: CAPM rewards ONLY systematic (market-wide) risk measured by beta. Unsystematic (firm-specific) risk earns NO reward because it can be diversified away.

Sheet Security Market Line
B1: SECURITY MARKET LINE (SML) — Investment Decision Framework
B3: Market Parameters (Linked from Inputs)
C4: Risk-Free Rate Rf | D4: =Inputs!$D$22 -> 0.05
C5: Market Return E(Rm) | D5: 0.14
C6: Market Risk Premium = E(Rm) – Rf | D6: =Inputs!$D$23-Inputs!$D$22 -> 0.07
B8: SML Data Points (β from 0 to 2, for chart)
C9: Beta β | D9: SML Required Return E(Ri)
C10: =0/10 -> 0 | D10: =Inputs!$D$22+(0/10)*(Inputs!$D$23-Inputs!$D$22) -> 0.05
C11: =1/10 -> 0.1 | D11: =Inputs!$D$22+(1/10)*(Inputs!$D$23-Inputs!$D$22) -> 0.057
C12: =2/10 -> 0.2 | D12: =Inputs!$D$22+(2/10)*(Inputs!$D$23-Inputs!$D$22) -> 0.064
C13: =3/10 -> 0.3 | D13: =Inputs!$D$22+(3/10)*(Inputs!$D$23-Inputs!$D$22) -> 0.071
C14: =4/10 -> 0.4 | D14: =Inputs!$D$22+(4/10)*(Inputs!$D$23-Inputs!$D$22) -> 0.078
C15: =5/10 -> 0.5 | D15: =Inputs!$D$22+(5/10)*(Inputs!$D$23-Inputs!$D$22) -> 0.085
C16: =6/10 -> 0.6 | D16: =Inputs!$D$22+(6/10)*(Inputs!$D$23-Inputs!$D$22) -> 0.092
C17: =7/10 -> 0.7 | D17: =Inputs!$D$22+(7/10)*(Inputs!$D$23-Inputs!$D$22) -> 0.099
C18: =8/10 -> 0.8 | D18: =Inputs!$D$22+(8/10)*(Inputs!$D$23-Inputs!$D$22) -> 0.106
C19: =9/10 -> 0.9 | D19: =Inputs!$D$22+(9/10)*(Inputs!$D$23-Inputs!$D$22) -> 0.113
C20: =10/10 -> 1 | D20: =Inputs!$D$22+(10/10)*(Inputs!$D$23-Inputs!$D$22) -> 0.12
C21: =11/10 -> 1.1 | D21: =Inputs!$D$22+(11/10)*(Inputs!$D$23-Inputs!$D$22) -> 0.127
C22: =12/10 -> 1.2 | D22: =Inputs!$D$22+(12/10)*(Inputs!$D$23-Inputs!$D$22) -> 0.134
C23: =13/10 -> 1.3 | D23: =Inputs!$D$22+(13/10)*(Inputs!$D$23-Inputs!$D$22) -> 0.141
C24: =14/10 -> 1.4 | D24: =Inputs!$D$22+(14/10)*(Inputs!$D$23-Inputs!$D$22) -> 0.148
C25: =15/10 -> 1.5 | D25: =Inputs!$D$22+(15/10)*(Inputs!$D$23-Inputs!$D$22) -> 0.155
C26: =16/10 -> 1.6 | D26: =Inputs!$D$22+(16/10)*(Inputs!$D$23-Inputs!$D$22) -> 0.162
C27: =17/10 -> 1.7 | D27: =Inputs!$D$22+(17/10)*(Inputs!$D$23-Inputs!$D$22) -> 0.169
C28: =18/10 -> 1.8 | D28: =Inputs!$D$22+(18/10)*(Inputs!$D$23-Inputs!$D$22) -> 0.176
C29: =19/10 -> 1.9 | D29: =Inputs!$D$22+(19/10)*(Inputs!$D$23-Inputs!$D$22) -> 0.183
C30: =20/10 -> 2 | D30: =Inputs!$D$22+(20/10)*(Inputs!$D$23-Inputs!$D$22) -> 0.19
B32: Market Portfolio (β=1): | C32: 1 | D32: =Inputs!$D$23 -> 0.12
B33: Risk-Free Asset (β=0): | C33: 0 | D33: =Inputs!$D$22 -> 0.05
B35: Example Securities: Above, On, or Below the SML
C36: Security | D36: Beta β | E36: Expected Return E(Ri) | F36: Required Return (CAPM) | G36: Alpha α | H36: Investment Decision
C37: Security A | D37: 0.8 | E37: 0.11 | F37: =Inputs!$D$22+0.8*(Inputs!$D$23-Inputs!$D$22) -> 0.106 | G37: =E37-F37 -> 0.004 | H37: =IF(G37>0.0001,"UNDERVALUED — BUY",IF(G37<-0.0001,"OVERVALUED — SELL","FAIRLY VALUED — HOLD")) -> UNDERVALUED — BUY
C38: Security B | D38: 1.2 | E38: 0.15 | F38: =Inputs!$D$22+1.2*(Inputs!$D$23-Inputs!$D$22) -> 0.134 | G38: =E38-F38 -> 0.016 | H38: =IF(G38>0.0001,"UNDERVALUED — BUY",IF(G38<-0.0001,"OVERVALUED — SELL","FAIRLY VALUED — HOLD")) -> UNDERVALUED — BUY
C39: Security C | D39: 1.5 | E39: 0.12 | F39: =Inputs!$D$22+1.5*(Inputs!$D$23-Inputs!$D$22) -> 0.155 | G39: =E39-F39 -> -0.035 | H39: =IF(G39>0.0001,"UNDERVALUED — BUY",IF(G39<-0.0001,"OVERVALUED — SELL","FAIRLY VALUED — HOLD")) -> OVERVALUED — SELL
B42: SML DECISION RULE (based on Alpha = Expected Return – CAPM Required Return): • Alpha > 0 → UNDERVALUED: Expected return > Required return → Plot ABOVE SML → BUY • Alpha = 0 → FAIRLY VALUED: Expected return = Required return → Plot ON SML → HOLD • Alpha < 0 → OVERVALUED: Expected return < Required return → Plot BELOW SML → SELL Note: SML uses BETA (systematic risk) on X-axis. CML uses STANDARD DEVIATION (total risk). SML applies to ALL assets. CML applies ONLY to efficiently diversified portfolios.

Sheet Dashboard
B1: TEACHING DASHBOARD — Live Classroom Summary View
B3: Input Summary (Change Values on Inputs Sheet) | F3: Key Output Summary (Auto-Calculated — All Formula-Driven)
C4: Asset A Return E(RA) | D4: =Inputs!$D$6 -> 0.15 | F4: Minimum Variance Portfolio
C5: Asset A Std Dev σA | D5: =Inputs!$D$7 -> 0.25 | F5: MVP Return | G5: ='Minimum Variance Portfolio'!D19 -> 0.086417657
C6: Asset B Return E(RB) | D6: =Inputs!$D$11 -> 0.08 | F6: MVP Std Dev σ | G6: ='Minimum Variance Portfolio'!D21 -> 0.11791914
C7: Asset B Std Dev σB | D7: =Inputs!$D$12 -> 0.12 | F7: MVP Weight in Asset A | G7: ='Minimum Variance Portfolio'!D15 -> 0.091680815
C8: Correlation ρAB | D8: =Inputs!$D$15 -> 0.3 | F8: MVP Weight in Asset B | G8: ='Minimum Variance Portfolio'!D16 -> 0.90831919
C9: Risk-Free Rate Rf | D9: =Inputs!$D$22 -> 0.05 | F9: MVP Sharpe Ratio | G9: ='Minimum Variance Portfolio'!D22 -> 0.30883584
C10: Market Return E(Rm) | D10: =Inputs!$D$23 -> 0.12
F11: Tangency Portfolio & CML
F12: Tangency Return E(RT) | G12: ='Capital Market Line'!D7 -> 0.1185
F13: Tangency Std Dev σT | G13: ='Capital Market Line'!D8 -> 0.16210259
F14: CML Slope (Tangency Sharpe) | G14: ='Capital Market Line'!D9 -> 0.4225719
F15: Max Sharpe in Risky Frontier | G15: ='Capital Market Line'!D4 -> 0.4225719
B41: CLASSROOM DISCUSSION QUESTIONS
B42: 1. Why does the frontier bend LEFT (toward lower risk) when correlation falls below +1?
B43: 2. What happens to the shape of the frontier when ρ = +1? Why does it become a straight line?
B44: 3. Can adding a RISKY asset to a portfolio actually REDUCE total portfolio risk? When and why?
B45: 4. The MVP minimises risk. Why is it NOT necessarily the optimal portfolio for every investor?
B46: 5. Why does the CML DOMINATE the risky-asset-only Efficient Frontier for all investors?
B47: 6. CAPM rewards ONLY systematic risk (beta). Why does unsystematic risk earn no return premium?
B48: 7. If Security C plots BELOW the SML, what does that signal to an investor? What should they do?
